python_ytg/__init__.py
python_ytg/ytg.py
python_ytg-0.0.1.dist-info/METADATA
python_ytg-0.0.1.dist-info/RECORD
python_ytg-0.0.1.dist-info/WHEEL
python_ytg-0.0.1.dist-info/top_level.txt
