Metadata-Version: 2.1
Name: python-ytg
Version: 0.0.1
Summary: Easily use YourTextGuru API in Python.
Home-page: https://gitlab.com/databulle/python_ytg
Author: Julien Deneuville
Author-email: julien@databulle.com
License: MIT
Keywords: seo yourtextguru api google content optimization nlp
Platform: UNKNOWN
Classifier: Programming Language :: Python :: 3
Classifier: License :: OSI Approved :: MIT License
Classifier: Operating System :: OS Independent
Classifier: Topic :: Scientific/Engineering :: Information Analysis
Requires-Dist: requests
